[
    {
        "ticker":"VNM",
        "yearReport":2024,
        "lengthReport":2,
        "Cash and cash equivalents":1788254863348,
        "Unrealized foreign exchange gain\/loss":-5431153785,
        "Profit\/Loss from disposal of fixed assets":0,
        "Profit\/Loss from investing activities":-344871047097,
        "Interest Expense":64294446778,
        "Interest income and dividends":0,
        "Increase\/Decrease in receivables":-386731248915,
        "Increase\/Decrease in inventories":137207411891,
        "Increase\/Decrease in payables":357463397480,
        "Increase\/Decrease in prepaid expenses":90310558794,
        "Interest paid":-80643224421,
        "Business Income Tax paid":-384854168143,
        "Other receipts from operating activities":0,
        "Other payments on operating activities":-55221142079,
        "Net cash inflows\/outflows from operating activities":3318424925023,
        "Proceeds from disposal of fixed assets":30356023115,
        "Investment in other entities":0,
        "Proceeds from divestment in other entities":0,
        "Payments for share repurchases":0,
        "Proceeds from borrowings":5106918716760,
        "Repayment of borrowings":-3967402455216,
        "Dividends paid":-1918097497500,
        "Net increase\/decrease in cash and cash equivalents":-597839008728,
        "Foreign exchange differences Adjustment":8147032908,
        "Cash and Cash Equivalents at the end of period":1198562887528,
        "Depreciation and Amortisation":523825243110,
        "Operating profit before changes in working capital":3640893340416,
        "Purchase of fixed assets":-589564090578,
        "Gain on Dividend":262540916333,
        "Net Cash Flows from Investing Activities":-3183889697795,
        "Increase in charter captial":46207000000,
        "Cash flows from financial activities":-732374235956,
        "Collection of loans, proceeds from sales of debts instruments (Bn. VND)":-34235481165,
        "Loans granted, purchases of debt instruments (Bn. VND)":-2852987065500
    },
    {
        "ticker":"VNM",
        "yearReport":2024,
        "lengthReport":1,
        "Cash and cash equivalents":2912027359925,
        "Unrealized foreign exchange gain\/loss":-2331136075,
        "Profit\/Loss from disposal of fixed assets":0,
        "Profit\/Loss from investing activities":-344903447103,
        "Interest Expense":86395425954,
        "Interest income and dividends":0,
        "Increase\/Decrease in receivables":751974551131,
        "Increase\/Decrease in inventories":-762680286964,
        "Increase\/Decrease in payables":-521637847835,
        "Increase\/Decrease in prepaid expenses":-55379919602,
        "Interest paid":-138840952227,
        "Business Income Tax paid":-846730006438,
        "Other receipts from operating activities":0,
        "Other payments on operating activities":-531465803150,
        "Net cash inflows\/outflows from operating activities":907549198441,
        "Proceeds from disposal of fixed assets":22762588100,
        "Investment in other entities":0,
        "Proceeds from divestment in other entities":0,
        "Payments for share repurchases":0,
        "Proceeds from borrowings":2764598729970,
        "Repayment of borrowings":-4403425616970,
        "Dividends paid":-1044977722500,
        "Net increase\/decrease in cash and cash equivalents":-1127467857189,
        "Foreign exchange differences Adjustment":3695360612,
        "Cash and Cash Equivalents at the end of period":1788254863348,
        "Depreciation and Amortisation":504624077696,
        "Operating profit before changes in working capital":3012309463526,
        "Purchase of fixed assets":-378452282107,
        "Gain on Dividend":294041766712,
        "Net Cash Flows from Investing Activities":-27412446130,
        "Increase in charter captial":676200000000,
        "Cash flows from financial activities":-2007604609500,
        "Collection of loans, proceeds from sales of debts instruments (Bn. VND)":34235481165,
        "Loans granted, purchases of debt instruments (Bn. VND)":0
    },
    {
        "ticker":"VNM",
        "yearReport":2023,
        "lengthReport":4,
        "Cash and cash equivalents":6875567986039,
        "Unrealized foreign exchange gain\/loss":3572601291,
        "Profit\/Loss from disposal of fixed assets":0,
        "Profit\/Loss from investing activities":-544852427188,
        "Interest Expense":96231603161,
        "Interest income and dividends":0,
        "Increase\/Decrease in receivables":-764132499014,
        "Increase\/Decrease in inventories":-578146961187,
        "Increase\/Decrease in payables":-442381898850,
        "Increase\/Decrease in prepaid expenses":12023053003,
        "Interest paid":-58107360372,
        "Business Income Tax paid":-835119449240,
        "Other receipts from operating activities":0,
        "Other payments on operating activities":-57098048554,
        "Net cash inflows\/outflows from operating activities":485275682082,
        "Proceeds from disposal of fixed assets":28701388834,
        "Investment in other entities":0,
        "Proceeds from divestment in other entities":10570000000,
        "Payments for share repurchases":0,
        "Proceeds from borrowings":3046045712825,
        "Repayment of borrowings":-1746367168668,
        "Dividends paid":-5190521652450,
        "Net increase\/decrease in cash and cash equivalents":-3966512781157,
        "Foreign exchange differences Adjustment":2972155043,
        "Cash and Cash Equivalents at the end of period":2912027359925,
        "Depreciation and Amortisation":763406685584,
        "Operating profit before changes in working capital":3208238846296,
        "Purchase of fixed assets":-519884863780,
        "Gain on Dividend":495280136848,
        "Net Cash Flows from Investing Activities":-560752481954,
        "Increase in charter captial":-192872992,
        "Cash flows from financial activities":-3891035981285,
        "Collection of loans, proceeds from sales of debts instruments (Bn. VND)":0,
        "Loans granted, purchases of debt instruments (Bn. VND)":-575419143856
    },
    {
        "ticker":"VNM",
        "yearReport":2023,
        "lengthReport":3,
        "Cash and cash equivalents":1582506692207,
        "Unrealized foreign exchange gain\/loss":2940062682,
        "Profit\/Loss from disposal of fixed assets":0,
        "Profit\/Loss from investing activities":-414801393695,
        "Interest Expense":79600679532,
        "Interest income and dividends":0,
        "Increase\/Decrease in receivables":300186241796,
        "Increase\/Decrease in inventories":516836588561,
        "Increase\/Decrease in payables":392228055999,
        "Increase\/Decrease in prepaid expenses":24881897683,
        "Interest paid":-77085630938,
        "Business Income Tax paid":-307037904564,
        "Other receipts from operating activities":0,
        "Other payments on operating activities":-218978665662,
        "Net cash inflows\/outflows from operating activities":3941939295009,
        "Proceeds from disposal of fixed assets":27787128715,
        "Investment in other entities":-23894832735,
        "Proceeds from divestment in other entities":0,
        "Payments for share repurchases":0,
        "Proceeds from borrowings":1011758029279,
        "Repayment of borrowings":-279164172658,
        "Dividends paid":-135910000,
        "Net increase\/decrease in cash and cash equivalents":5289852520709,
        "Foreign exchange differences Adjustment":3208773123,
        "Cash and Cash Equivalents at the end of period":6875567986039,
        "Depreciation and Amortisation":491605000895,
        "Operating profit before changes in working capital":3310908712134,
        "Purchase of fixed assets":-191415880964,
        "Gain on Dividend":463272969854,
        "Net Cash Flows from Investing Activities":463575397079,
        "Increase in charter captial":151879882000,
        "Cash flows from financial activities":884337828621,
        "Collection of loans, proceeds from sales of debts instruments (Bn. VND)":0,
        "Loans granted, purchases of debt instruments (Bn. VND)":187826012209
    },
    {
        "ticker":"VNM",
        "yearReport":2023,
        "lengthReport":2,
        "Cash and cash equivalents":2011202511723,
        "Unrealized foreign exchange gain\/loss":11071666376,
        "Profit\/Loss from disposal of fixed assets":0,
        "Profit\/Loss from investing activities":-373959695591,
        "Interest Expense":95970637757,
        "Interest income and dividends":0,
        "Increase\/Decrease in receivables":662820622520,
        "Increase\/Decrease in inventories":291256666371,
        "Increase\/Decrease in payables":-521773785211,
        "Increase\/Decrease in prepaid expenses":23859555186,
        "Interest paid":-98141291364,
        "Business Income Tax paid":-7391288214,
        "Other receipts from operating activities":0,
        "Other payments on operating activities":-89110014039,
        "Net cash inflows\/outflows from operating activities":3331419644827,
        "Proceeds from disposal of fixed assets":25484345483,
        "Investment in other entities":0,
        "Proceeds from divestment in other entities":0,
        "Payments for share repurchases":-142548827636,
        "Proceeds from borrowings":3233083516768,
        "Repayment of borrowings":-3789115747176,
        "Dividends paid":-35001066500,
        "Net increase\/decrease in cash and cash equivalents":-430191253330,
        "Foreign exchange differences Adjustment":1495433814,
        "Cash and Cash Equivalents at the end of period":1582506692207,
        "Depreciation and Amortisation":515807377104,
        "Operating profit before changes in working capital":3069899179578,
        "Purchase of fixed assets":-511069025115,
        "Gain on Dividend":183478453851,
        "Net Cash Flows from Investing Activities":-3366128773613,
        "Increase in charter captial":338100000000,
        "Cash flows from financial activities":-395482124544,
        "Collection of loans, proceeds from sales of debts instruments (Bn. VND)":-595311888127,
        "Loans granted, purchases of debt instruments (Bn. VND)":-2468710659705
    },
    {
        "ticker":"VNM",
        "yearReport":2023,
        "lengthReport":1,
        "Cash and cash equivalents":2299943527624,
        "Unrealized foreign exchange gain\/loss":-10136208614,
        "Profit\/Loss from disposal of fixed assets":0,
        "Profit\/Loss from investing activities":-308900756248,
        "Interest Expense":82291916805,
        "Interest income and dividends":0,
        "Increase\/Decrease in receivables":-443861503618,
        "Increase\/Decrease in inventories":-1251259683318,
        "Increase\/Decrease in payables":128549496304,
        "Increase\/Decrease in prepaid expenses":-52896323660,
        "Interest paid":-69373556896,
        "Business Income Tax paid":-414525307219,
        "Other receipts from operating activities":0,
        "Other payments on operating activities":-438254973999,
        "Net cash inflows\/outflows from operating activities":128788940445,
        "Proceeds from disposal of fixed assets":22907922254,
        "Investment in other entities":-11875000000,
        "Proceeds from divestment in other entities":0,
        "Payments for share repurchases":0,
        "Proceeds from borrowings":4497529706931,
        "Repayment of borrowings":-2462185467993,
        "Dividends paid":-2925937623000,
        "Net increase\/decrease in cash and cash equivalents":-287047095630,
        "Foreign exchange differences Adjustment":-1693920271,
        "Cash and Cash Equivalents at the end of period":2011202511723,
        "Depreciation and Amortisation":529307916114,
        "Operating profit before changes in working capital":2670410792851,
        "Purchase of fixed assets":-357267370903,
        "Gain on Dividend":225679908509,
        "Net Cash Flows from Investing Activities":474757347987,
        "Increase in charter captial":0,
        "Cash flows from financial activities":-890593384062,
        "Collection of loans, proceeds from sales of debts instruments (Bn. VND)":595311888127,
        "Loans granted, purchases of debt instruments (Bn. VND)":0
    },
    {
        "ticker":"VNM",
        "yearReport":2022,
        "lengthReport":4,
        "Cash and cash equivalents":2867857717514,
        "Unrealized foreign exchange gain\/loss":-37709125252,
        "Profit\/Loss from disposal of fixed assets":0,
        "Profit\/Loss from investing activities":-289871188461,
        "Interest Expense":53226546796,
        "Interest income and dividends":0,
        "Increase\/Decrease in receivables":-323856956229,
        "Increase\/Decrease in inventories":100113197805,
        "Increase\/Decrease in payables":587684749308,
        "Increase\/Decrease in prepaid expenses":-24722822830,
        "Interest paid":-72895032400,
        "Business Income Tax paid":-1182224363703,
        "Other receipts from operating activities":0,
        "Other payments on operating activities":-68713560259,
        "Net cash inflows\/outflows from operating activities":1637205135323,
        "Proceeds from disposal of fixed assets":31517617681,
        "Investment in other entities":-12275000000,
        "Proceeds from divestment in other entities":0,
        "Payments for share repurchases":0,
        "Proceeds from borrowings":74460006848,
        "Repayment of borrowings":-4575198249609,
        "Dividends paid":-68054218220,
        "Net increase\/decrease in cash and cash equivalents":-565286237309,
        "Foreign exchange differences Adjustment":-2627952581,
        "Cash and Cash Equivalents at the end of period":2299943527624,
        "Depreciation and Amortisation":518465696774,
        "Operating profit before changes in working capital":2621819923631,
        "Purchase of fixed assets":-544290990514,
        "Gain on Dividend":439122953860,
        "Net Cash Flows from Investing Activities":2028201088349,
        "Increase in charter captial":338100000000,
        "Cash flows from financial activities":-4230692460981,
        "Collection of loans, proceeds from sales of debts instruments (Bn. VND)":2114126507322,
        "Loans granted, purchases of debt instruments (Bn. VND)":0
    },
    {
        "ticker":"VNM",
        "yearReport":2022,
        "lengthReport":3,
        "Cash and cash equivalents":4507497088287,
        "Unrealized foreign exchange gain\/loss":8347587934,
        "Profit\/Loss from disposal of fixed assets":0,
        "Profit\/Loss from investing activities":-300066817563,
        "Interest Expense":49942302240,
        "Interest income and dividends":0,
        "Increase\/Decrease in receivables":145032717998,
        "Increase\/Decrease in inventories":1170617557118,
        "Increase\/Decrease in payables":49012854865,
        "Increase\/Decrease in prepaid expenses":-41625935038,
        "Interest paid":-30200578249,
        "Business Income Tax paid":-4319705578,
        "Other receipts from operating activities":0,
        "Other payments on operating activities":-270371253685,
        "Net cash inflows\/outflows from operating activities":4235275963748,
        "Proceeds from disposal of fixed assets":32678492852,
        "Investment in other entities":0,
        "Proceeds from divestment in other entities":0,
        "Payments for share repurchases":0,
        "Proceeds from borrowings":2108262740353,
        "Repayment of borrowings":-2424633276675,
        "Dividends paid":-5120390840250,
        "Net increase\/decrease in cash and cash equivalents":-1648250313249,
        "Foreign exchange differences Adjustment":8610942476,
        "Cash and Cash Equivalents at the end of period":2867857717514,
        "Depreciation and Amortisation":519932114467,
        "Operating profit before changes in working capital":3217130306317,
        "Purchase of fixed assets":-275135514383,
        "Gain on Dividend":338287929867,
        "Net Cash Flows from Investing Activities":-446764900425,
        "Increase in charter captial":0,
        "Cash flows from financial activities":-5436761376572,
        "Collection of loans, proceeds from sales of debts instruments (Bn. VND)":-542595808761,
        "Loans granted, purchases of debt instruments (Bn. VND)":0
    },
    {
        "ticker":"VNM",
        "yearReport":2022,
        "lengthReport":2,
        "Cash and cash equivalents":1680858133124,
        "Unrealized foreign exchange gain\/loss":18765937820,
        "Profit\/Loss from disposal of fixed assets":0,
        "Profit\/Loss from investing activities":-305838412194,
        "Interest Expense":36701642341,
        "Interest income and dividends":0,
        "Increase\/Decrease in receivables":111504280918,
        "Increase\/Decrease in inventories":554691597850,
        "Increase\/Decrease in payables":-288064121816,
        "Increase\/Decrease in prepaid expenses":27917606527,
        "Interest paid":-13859036144,
        "Business Income Tax paid":-313608928018,
        "Other receipts from operating activities":0,
        "Other payments on operating activities":-168342875725,
        "Net cash inflows\/outflows from operating activities":2810003575388,
        "Proceeds from disposal of fixed assets":41247791036,
        "Investment in other entities":0,
        "Proceeds from divestment in other entities":0,
        "Payments for share repurchases":0,
        "Proceeds from borrowings":-161958314770,
        "Repayment of borrowings":-1096336875705,
        "Dividends paid":-52516937250,
        "Net increase\/decrease in cash and cash equivalents":2820875323448,
        "Foreign exchange differences Adjustment":5763631715,
        "Cash and Cash Equivalents at the end of period":4507497088287,
        "Depreciation and Amortisation":519680313013,
        "Operating profit before changes in working capital":2899765051796,
        "Purchase of fixed assets":-376750770688,
        "Gain on Dividend":188785840560,
        "Net Cash Flows from Investing Activities":1321683875785,
        "Increase in charter captial":0,
        "Cash flows from financial activities":-1310812127725,
        "Collection of loans, proceeds from sales of debts instruments (Bn. VND)":1468401014877,
        "Loans granted, purchases of debt instruments (Bn. VND)":0
    },
    {
        "ticker":"VNM",
        "yearReport":2022,
        "lengthReport":1,
        "Cash and cash equivalents":2348551874348,
        "Unrealized foreign exchange gain\/loss":13818366371,
        "Profit\/Loss from disposal of fixed assets":0,
        "Profit\/Loss from investing activities":-290437323940,
        "Interest Expense":26168600367,
        "Interest income and dividends":0,
        "Increase\/Decrease in receivables":-220757350364,
        "Increase\/Decrease in inventories":-974159283034,
        "Increase\/Decrease in payables":-734666056911,
        "Increase\/Decrease in prepaid expenses":-34688910773,
        "Interest paid":-24349437056,
        "Business Income Tax paid":-475136766140,
        "Other receipts from operating activities":0,
        "Other payments on operating activities":-556210692528,
        "Net cash inflows\/outflows from operating activities":144788502057,
        "Proceeds from disposal of fixed assets":31681656288,
        "Investment in other entities":-30900000000,
        "Proceeds from divestment in other entities":0,
        "Payments for share repurchases":0,
        "Proceeds from borrowings":4236765622155,
        "Repayment of borrowings":-2692851399800,
        "Dividends paid":-2925937623000,
        "Net increase\/decrease in cash and cash equivalents":-667583447199,
        "Foreign exchange differences Adjustment":-110294025,
        "Cash and Cash Equivalents at the end of period":1680858133124,
        "Depreciation and Amortisation":537371734423,
        "Operating profit before changes in working capital":3164756998863,
        "Purchase of fixed assets":-260736777031,
        "Gain on Dividend":234823238963,
        "Net Cash Flows from Investing Activities":569651451389,
        "Increase in charter captial":0,
        "Cash flows from financial activities":-1382023400645,
        "Collection of loans, proceeds from sales of debts instruments (Bn. VND)":594783333169,
        "Loans granted, purchases of debt instruments (Bn. VND)":0
    },
    {
        "ticker":"VNM",
        "yearReport":2021,
        "lengthReport":4,
        "Cash and cash equivalents":2051857098275,
        "Unrealized foreign exchange gain\/loss":-945595838,
        "Profit\/Loss from disposal of fixed assets":0,
        "Profit\/Loss from investing activities":-110310185077,
        "Interest Expense":23446278323,
        "Interest income and dividends":0,
        "Increase\/Decrease in receivables":196920958051,
        "Increase\/Decrease in inventories":-504395056818,
        "Increase\/Decrease in payables":133391669295,
        "Increase\/Decrease in prepaid expenses":17733217659,
        "Interest paid":-38442032429,
        "Business Income Tax paid":-1443094434863,
        "Other receipts from operating activities":0,
        "Other payments on operating activities":-163732710514,
        "Net cash inflows\/outflows from operating activities":1310461126514,
        "Proceeds from disposal of fixed assets":34591138702,
        "Investment in other entities":-18905857575,
        "Proceeds from divestment in other entities":0,
        "Payments for share repurchases":0,
        "Proceeds from borrowings":3644283404234,
        "Repayment of borrowings":-3305731540656,
        "Dividends paid":-44669622900,
        "Net increase\/decrease in cash and cash equivalents":283787024259,
        "Foreign exchange differences Adjustment":12907751814,
        "Cash and Cash Equivalents at the end of period":2348551874348,
        "Depreciation and Amortisation":534531930191,
        "Operating profit before changes in working capital":3112079516133,
        "Purchase of fixed assets":-476734934789,
        "Gain on Dividend":388908926691,
        "Net Cash Flows from Investing Activities":-1343096342933,
        "Increase in charter captial":22540000000,
        "Cash flows from financial activities":316422240678,
        "Collection of loans, proceeds from sales of debts instruments (Bn. VND)":0,
        "Loans granted, purchases of debt instruments (Bn. VND)":-1270955615962
    },
    {
        "ticker":"VNM",
        "yearReport":2021,
        "lengthReport":3,
        "Cash and cash equivalents":1663036014269,
        "Unrealized foreign exchange gain\/loss":4153986284,
        "Profit\/Loss from disposal of fixed assets":0,
        "Profit\/Loss from investing activities":-38161311220,
        "Interest Expense":24374567105,
        "Interest income and dividends":0,
        "Increase\/Decrease in receivables":240227639444,
        "Increase\/Decrease in inventories":361721935211,
        "Increase\/Decrease in payables":236770041444,
        "Increase\/Decrease in prepaid expenses":40181414369,
        "Interest paid":-35611697178,
        "Business Income Tax paid":-351391408402,
        "Other receipts from operating activities":0,
        "Other payments on operating activities":-288672021480,
        "Net cash inflows\/outflows from operating activities":4055436695667,
        "Proceeds from disposal of fixed assets":37633032244,
        "Investment in other entities":0,
        "Proceeds from divestment in other entities":0,
        "Payments for share repurchases":0,
        "Proceeds from borrowings":2331816027715,
        "Repayment of borrowings":-2779299380232,
        "Dividends paid":-3134933167500,
        "Net increase\/decrease in cash and cash equivalents":400105993345,
        "Foreign exchange differences Adjustment":-11284909339,
        "Cash and Cash Equivalents at the end of period":2051857098275,
        "Depreciation and Amortisation":539359820888,
        "Operating profit before changes in working capital":3852210792259,
        "Purchase of fixed assets":-638146714343,
        "Gain on Dividend":316720627688,
        "Net Cash Flows from Investing Activities":-72914182305,
        "Increase in charter captial":0,
        "Cash flows from financial activities":-3582416520017,
        "Collection of loans, proceeds from sales of debts instruments (Bn. VND)":0,
        "Loans granted, purchases of debt instruments (Bn. VND)":210878872106
    },
    {
        "ticker":"VNM",
        "yearReport":2021,
        "lengthReport":2,
        "Cash and cash equivalents":1197956795582,
        "Unrealized foreign exchange gain\/loss":-3585620065,
        "Profit\/Loss from disposal of fixed assets":16223729056,
        "Profit\/Loss from investing activities":288270458461,
        "Interest Expense":28072255034,
        "Interest income and dividends":-525955313779,
        "Increase\/Decrease in receivables":-912285302715,
        "Increase\/Decrease in inventories":-480784663584,
        "Increase\/Decrease in payables":383647905131,
        "Increase\/Decrease in prepaid expenses":89748086761,
        "Interest paid":-8489668682,
        "Business Income Tax paid":-12962786832,
        "Other receipts from operating activities":0,
        "Other payments on operating activities":-75004249781,
        "Net cash inflows\/outflows from operating activities":2877367183580,
        "Proceeds from disposal of fixed assets":31248056978,
        "Investment in other entities":-4321875000,
        "Proceeds from divestment in other entities":1336500000,
        "Payments for share repurchases":0,
        "Proceeds from borrowings":911102897822,
        "Repayment of borrowings":-682111123596,
        "Dividends paid":-2351459800500,
        "Net increase\/decrease in cash and cash equivalents":462380259163,
        "Foreign exchange differences Adjustment":2698959524,
        "Cash and Cash Equivalents at the end of period":1663036014269,
        "Depreciation and Amortisation":547756789868,
        "Operating profit before changes in working capital":3893497863282,
        "Purchase of fixed assets":-241674993139,
        "Gain on Dividend":149433956359,
        "Net Cash Flows from Investing Activities":-488518898143,
        "Increase in charter captial":196000000000,
        "Cash flows from financial activities":-1926468026274,
        "Collection of loans, proceeds from sales of debts instruments (Bn. VND)":0,
        "Loans granted, purchases of debt instruments (Bn. VND)":-424540543341
    },
    {
        "ticker":"VNM",
        "yearReport":2021,
        "lengthReport":1,
        "Cash and cash equivalents":2111242815581,
        "Unrealized foreign exchange gain\/loss":-1281139009,
        "Profit\/Loss from disposal of fixed assets":5187526637,
        "Profit\/Loss from investing activities":-250400369913,
        "Interest Expense":12905990201,
        "Interest income and dividends":0,
        "Increase\/Decrease in receivables":-41714113141,
        "Increase\/Decrease in inventories":-1637223057031,
        "Increase\/Decrease in payables":730238705657,
        "Increase\/Decrease in prepaid expenses":-147546962653,
        "Interest paid":-15796286643,
        "Business Income Tax paid":-549149282272,
        "Other receipts from operating activities":0,
        "Other payments on operating activities":-644131581434,
        "Net cash inflows\/outflows from operating activities":1188708558132,
        "Proceeds from disposal of fixed assets":30432767605,
        "Investment in other entities":0,
        "Proceeds from divestment in other entities":0,
        "Payments for share repurchases":0,
        "Proceeds from borrowings":2709758030232,
        "Repayment of borrowings":-784318154711,
        "Dividends paid":-2089695872250,
        "Net increase\/decrease in cash and cash equivalents":-904945437872,
        "Foreign exchange differences Adjustment":-8340582127,
        "Cash and Cash Equivalents at the end of period":1197956795582,
        "Depreciation and Amortisation":499689193833,
        "Operating profit before changes in working capital":3494031135649,
        "Purchase of fixed assets":-174468716999,
        "Gain on Dividend":145015833823,
        "Net Cash Flows from Investing Activities":-2028718663828,
        "Increase in charter captial":99320664553,
        "Cash flows from financial activities":-64935332176,
        "Collection of loans, proceeds from sales of debts instruments (Bn. VND)":150000000,
        "Loans granted, purchases of debt instruments (Bn. VND)":-2029848548257
    },
    {
        "ticker":"VNM",
        "yearReport":2020,
        "lengthReport":4,
        "Cash and cash equivalents":2335881481579,
        "Unrealized foreign exchange gain\/loss":17776990028,
        "Profit\/Loss from disposal of fixed assets":14082316639,
        "Profit\/Loss from investing activities":-297044792097,
        "Interest Expense":25857854618,
        "Interest income and dividends":-290663117492,
        "Increase\/Decrease in receivables":338096748719,
        "Increase\/Decrease in inventories":219062180306,
        "Increase\/Decrease in payables":-342930345042,
        "Increase\/Decrease in prepaid expenses":-13902968116,
        "Interest paid":-24747091435,
        "Business Income Tax paid":-1376173589619,
        "Other receipts from operating activities":0,
        "Other payments on operating activities":-242254695396,
        "Net cash inflows\/outflows from operating activities":1623081986175,
        "Proceeds from disposal of fixed assets":41623645123,
        "Investment in other entities":0,
        "Proceeds from divestment in other entities":15660460001,
        "Payments for share repurchases":0,
        "Proceeds from borrowings":3513640917035,
        "Repayment of borrowings":-2628425044234,
        "Dividends paid":-3515487388000,
        "Net increase\/decrease in cash and cash equivalents":-223315185921,
        "Foreign exchange differences Adjustment":-1323480077,
        "Cash and Cash Equivalents at the end of period":2111242815581,
        "Depreciation and Amortisation":545413737797,
        "Operating profit before changes in working capital":3065931746758,
        "Purchase of fixed assets":-331440622408,
        "Gain on Dividend":679703952898,
        "Net Cash Flows from Investing Activities":783874343103,
        "Increase in charter captial":0,
        "Cash flows from financial activities":-2630271515199,
        "Collection of loans, proceeds from sales of debts instruments (Bn. VND)":22720498078,
        "Loans granted, purchases of debt instruments (Bn. VND)":355606409411
    },
    {
        "ticker":"VNM",
        "yearReport":2020,
        "lengthReport":3,
        "Cash and cash equivalents":2176667357252,
        "Unrealized foreign exchange gain\/loss":-14810127185,
        "Profit\/Loss from disposal of fixed assets":9964216884,
        "Profit\/Loss from investing activities":-469477854,
        "Interest Expense":38257217439,
        "Interest income and dividends":-336241399386,
        "Increase\/Decrease in receivables":-156108957411,
        "Increase\/Decrease in inventories":369339834301,
        "Increase\/Decrease in payables":154975681705,
        "Increase\/Decrease in prepaid expenses":42452692812,
        "Interest paid":-97654097013,
        "Business Income Tax paid":-440226814798,
        "Other receipts from operating activities":0,
        "Other payments on operating activities":-275703469573,
        "Net cash inflows\/outflows from operating activities":3749005315011,
        "Proceeds from disposal of fixed assets":45232304785,
        "Investment in other entities":0,
        "Proceeds from divestment in other entities":56700000,
        "Payments for share repurchases":0,
        "Proceeds from borrowings":2931509588341,
        "Repayment of borrowings":-2703692788327,
        "Dividends paid":-2612066540460,
        "Net increase\/decrease in cash and cash equivalents":160817136963,
        "Foreign exchange differences Adjustment":-1603012636,
        "Cash and Cash Equivalents at the end of period":2335881481579,
        "Depreciation and Amortisation":551231227788,
        "Operating profit before changes in working capital":4151930444988,
        "Purchase of fixed assets":-259511681417,
        "Gain on Dividend":239814007393,
        "Net Cash Flows from Investing Activities":-1203938437602,
        "Increase in charter captial":0,
        "Cash flows from financial activities":-2384249740446,
        "Collection of loans, proceeds from sales of debts instruments (Bn. VND)":-19798404571,
        "Loans granted, purchases of debt instruments (Bn. VND)":-1209731363792
    },
    {
        "ticker":"VNM",
        "yearReport":2020,
        "lengthReport":2,
        "Cash and cash equivalents":1379711866875,
        "Unrealized foreign exchange gain\/loss":-70182197587,
        "Profit\/Loss from disposal of fixed assets":10375293005,
        "Profit\/Loss from investing activities":-14911917546,
        "Interest Expense":37641854799,
        "Interest income and dividends":-295663544495,
        "Increase\/Decrease in receivables":-798813712450,
        "Increase\/Decrease in inventories":-41272718213,
        "Increase\/Decrease in payables":-251611274053,
        "Increase\/Decrease in prepaid expenses":116164637797,
        "Interest paid":-43161271053,
        "Business Income Tax paid":-3883737667,
        "Other receipts from operating activities":0,
        "Other payments on operating activities":-64173681018,
        "Net cash inflows\/outflows from operating activities":2928440096694,
        "Proceeds from disposal of fixed assets":34914151212,
        "Investment in other entities":0,
        "Proceeds from divestment in other entities":5914424085,
        "Payments for share repurchases":-14364328733,
        "Proceeds from borrowings":363879305622,
        "Repayment of borrowings":-190086416469,
        "Dividends paid":-9682167601,
        "Net increase\/decrease in cash and cash equivalents":796556910591,
        "Foreign exchange differences Adjustment":398579786,
        "Cash and Cash Equivalents at the end of period":2176667357252,
        "Depreciation and Amortisation":556761193198,
        "Operating profit before changes in working capital":4015191853351,
        "Purchase of fixed assets":-285938583140,
        "Gain on Dividend":102167616423,
        "Net Cash Flows from Investing Activities":-2281629578922,
        "Increase in charter captial":0,
        "Cash flows from financial activities":149746392819,
        "Collection of loans, proceeds from sales of debts instruments (Bn. VND)":13050562820,
        "Loans granted, purchases of debt instruments (Bn. VND)":-2151737750322
    },
    {
        "ticker":"VNM",
        "yearReport":2020,
        "lengthReport":1,
        "Cash and cash equivalents":2665194638452,
        "Unrealized foreign exchange gain\/loss":67852556191,
        "Profit\/Loss from disposal of fixed assets":8717274881,
        "Profit\/Loss from investing activities":11789710907,
        "Interest Expense":42061538321,
        "Interest income and dividends":-255224496408,
        "Increase\/Decrease in receivables":-98128897274,
        "Increase\/Decrease in inventories":-817204595821,
        "Increase\/Decrease in payables":226768277649,
        "Increase\/Decrease in prepaid expenses":-121073448246,
        "Interest paid":-47206055606,
        "Business Income Tax paid":-466046765343,
        "Other receipts from operating activities":0,
        "Other payments on operating activities":-654774677678,
        "Net cash inflows\/outflows from operating activities":1879641990348,
        "Proceeds from disposal of fixed assets":28572651322,
        "Investment in other entities":-8134000,
        "Proceeds from divestment in other entities":0,
        "Payments for share repurchases":0,
        "Proceeds from borrowings":960114694496,
        "Repayment of borrowings":-231397975055,
        "Dividends paid":-1790475448000,
        "Net increase\/decrease in cash and cash equivalents":-1282433226101,
        "Foreign exchange differences Adjustment":-3049545476,
        "Cash and Cash Equivalents at the end of period":1379711866875,
        "Depreciation and Amortisation":555460462969,
        "Operating profit before changes in working capital":3857284664651,
        "Purchase of fixed assets":-387926108738,
        "Gain on Dividend":118860284353,
        "Net Cash Flows from Investing Activities":-2100316487890,
        "Increase in charter captial":0,
        "Cash flows from financial activities":-1061758728559,
        "Collection of loans, proceeds from sales of debts instruments (Bn. VND)":15592992000,
        "Loans granted, purchases of debt instruments (Bn. VND)":-1875408172827
    },
    {
        "ticker":"VNM",
        "yearReport":2019,
        "lengthReport":4,
        "Cash and cash equivalents":1043473767363,
        "Unrealized foreign exchange gain\/loss":7871927410,
        "Profit\/Loss from disposal of fixed assets":6348242528,
        "Profit\/Loss from investing activities":0,
        "Interest Expense":35838396433,
        "Interest income and dividends":-203628180156,
        "Increase\/Decrease in receivables":1086934191849,
        "Increase\/Decrease in inventories":179425917988,
        "Increase\/Decrease in payables":-134249653741,
        "Increase\/Decrease in prepaid expenses":18374333821,
        "Interest paid":-59045450382,
        "Business Income Tax paid":-830474047043,
        "Other receipts from operating activities":0,
        "Other payments on operating activities":-7738740515,
        "Net cash inflows\/outflows from operating activities":3245522579047,
        "Proceeds from disposal of fixed assets":41889685185,
        "Investment in other entities":-674953145601,
        "Proceeds from divestment in other entities":-5094607490,
        "Payments for share repurchases":0,
        "Proceeds from borrowings":2793809369363,
        "Repayment of borrowings":-1606120787370,
        "Dividends paid":0,
        "Net increase\/decrease in cash and cash equivalents":1621287645619,
        "Foreign exchange differences Adjustment":433225470,
        "Cash and Cash Equivalents at the end of period":2665194638452,
        "Depreciation and Amortisation":502928809106,
        "Operating profit before changes in working capital":2996776067070,
        "Purchase of fixed assets":-412682027575,
        "Gain on Dividend":388922232516,
        "Net Cash Flows from Investing Activities":-2811835315421,
        "Increase in charter captial":-88200000,
        "Cash flows from financial activities":1187600381993,
        "Collection of loans, proceeds from sales of debts instruments (Bn. VND)":603109511,
        "Loans granted, purchases of debt instruments (Bn. VND)":-2150520561967
    },
    {
        "ticker":"VNM",
        "yearReport":2019,
        "lengthReport":3,
        "Cash and cash equivalents":1676491290318,
        "Unrealized foreign exchange gain\/loss":-678177168,
        "Profit\/Loss from disposal of fixed assets":13281469680,
        "Profit\/Loss from investing activities":0,
        "Interest Expense":27795829812,
        "Interest income and dividends":-191575608715,
        "Increase\/Decrease in receivables":-141321492048,
        "Increase\/Decrease in inventories":466516959344,
        "Increase\/Decrease in payables":222731981563,
        "Increase\/Decrease in prepaid expenses":118497985945,
        "Interest paid":-81161524995,
        "Business Income Tax paid":-499993419017,
        "Other receipts from operating activities":0,
        "Other payments on operating activities":-272923098054,
        "Net cash inflows\/outflows from operating activities":3445221404402,
        "Proceeds from disposal of fixed assets":28996148615,
        "Investment in other entities":-82911895211,
        "Proceeds from divestment in other entities":0,
        "Payments for share repurchases":-21047760,
        "Proceeds from borrowings":2926898806392,
        "Repayment of borrowings":-2105756532596,
        "Dividends paid":-3482755388000,
        "Net increase\/decrease in cash and cash equivalents":-628514687842,
        "Foreign exchange differences Adjustment":-4502835113,
        "Cash and Cash Equivalents at the end of period":1043473767363,
        "Depreciation and Amortisation":494141498125,
        "Operating profit before changes in working capital":3632874011664,
        "Purchase of fixed assets":-515985946731,
        "Gain on Dividend":89883118829,
        "Net Cash Flows from Investing Activities":-1411975142780,
        "Increase in charter captial":-126787500,
        "Cash flows from financial activities":-2661760949464,
        "Collection of loans, proceeds from sales of debts instruments (Bn. VND)":638871538,
        "Loans granted, purchases of debt instruments (Bn. VND)":-932595439820
    },
    {
        "ticker":"VNM",
        "yearReport":2019,
        "lengthReport":2,
        "Cash and cash equivalents":1209154406312,
        "Unrealized foreign exchange gain\/loss":468890998,
        "Profit\/Loss from disposal of fixed assets":10580680034,
        "Profit\/Loss from investing activities":162399003185,
        "Interest Expense":25355145802,
        "Interest income and dividends":-338335224702,
        "Increase\/Decrease in receivables":164882527594,
        "Increase\/Decrease in inventories":-348103866318,
        "Increase\/Decrease in payables":130558345289,
        "Increase\/Decrease in prepaid expenses":-24826984854,
        "Interest paid":-69330211449,
        "Business Income Tax paid":-294323955874,
        "Other receipts from operating activities":0,
        "Other payments on operating activities":-146351574871,
        "Net cash inflows\/outflows from operating activities":3320522923071,
        "Proceeds from disposal of fixed assets":21603005352,
        "Investment in other entities":-1324814577950,
        "Proceeds from divestment in other entities":6607824875,
        "Payments for share repurchases":-128807701000,
        "Proceeds from borrowings":2229905423649,
        "Repayment of borrowings":-1113102253725,
        "Dividends paid":-2612087527500,
        "Net increase\/decrease in cash and cash equivalents":465342214699,
        "Foreign exchange differences Adjustment":1994669307,
        "Cash and Cash Equivalents at the end of period":1676491290318,
        "Depreciation and Amortisation":478654208826,
        "Operating profit before changes in working capital":3908018643554,
        "Purchase of fixed assets":-551822503663,
        "Gain on Dividend":127792733879,
        "Net Cash Flows from Investing Activities":-1359394000736,
        "Increase in charter captial":128305350940,
        "Cash flows from financial activities":-1495786707636,
        "Collection of loans, proceeds from sales of debts instruments (Bn. VND)":646992000,
        "Loans granted, purchases of debt instruments (Bn. VND)":360592524771
    },
    {
        "ticker":"VNM",
        "yearReport":2019,
        "lengthReport":1,
        "Cash and cash equivalents":1522610167671,
        "Unrealized foreign exchange gain\/loss":-1204432181,
        "Profit\/Loss from disposal of fixed assets":13753677997,
        "Profit\/Loss from investing activities":-163912220570,
        "Interest Expense":19835521940,
        "Interest income and dividends":12607699916,
        "Increase\/Decrease in receivables":-736900175446,
        "Increase\/Decrease in inventories":104156418177,
        "Increase\/Decrease in payables":-618843746648,
        "Increase\/Decrease in prepaid expenses":-95636203348,
        "Interest paid":-18379368663,
        "Business Income Tax paid":-408800744034,
        "Other receipts from operating activities":0,
        "Other payments on operating activities":-545135630656,
        "Net cash inflows\/outflows from operating activities":1398661635170,
        "Proceeds from disposal of fixed assets":21601148510,
        "Investment in other entities":-75558716069,
        "Proceeds from divestment in other entities":0,
        "Payments for share repurchases":127669500000,
        "Proceeds from borrowings":2476161669254,
        "Repayment of borrowings":-1408133072360,
        "Dividends paid":-1741407855000,
        "Net increase\/decrease in cash and cash equivalents":-312040154607,
        "Foreign exchange differences Adjustment":-1415606752,
        "Cash and Cash Equivalents at the end of period":1209154406312,
        "Depreciation and Amortisation":472348259477,
        "Operating profit before changes in working capital":3718201085788,
        "Purchase of fixed assets":-677758728707,
        "Gain on Dividend":59192929151,
        "Net Cash Flows from Investing Activities":-1164670393231,
        "Increase in charter captial":-321638440,
        "Cash flows from financial activities":-546031396546,
        "Collection of loans, proceeds from sales of debts instruments (Bn. VND)":709224499,
        "Loans granted, purchases of debt instruments (Bn. VND)":-492856250615
    },
    {
        "ticker":"VNM",
        "yearReport":2018,
        "lengthReport":4,
        "Cash and cash equivalents":630784664818,
        "Unrealized foreign exchange gain\/loss":-3513282284,
        "Profit\/Loss from disposal of fixed assets":31287841927,
        "Profit\/Loss from investing activities":-12621228032,
        "Interest Expense":13558039918,
        "Interest income and dividends":-155905033876,
        "Increase\/Decrease in receivables":631935457172,
        "Increase\/Decrease in inventories":-1260296240064,
        "Increase\/Decrease in payables":1198124725250,
        "Increase\/Decrease in prepaid expenses":44057075460,
        "Interest paid":-73679724730,
        "Business Income Tax paid":-812899793394,
        "Other receipts from operating activities":0,
        "Other payments on operating activities":-97641858898,
        "Net cash inflows\/outflows from operating activities":2639187937754,
        "Proceeds from disposal of fixed assets":24503898262,
        "Investment in other entities":0,
        "Proceeds from divestment in other entities":16955703509,
        "Payments for share repurchases":-634110920,
        "Proceeds from borrowings":2477404795723,
        "Repayment of borrowings":-2401212316800,
        "Dividends paid":0,
        "Net increase\/decrease in cash and cash equivalents":893503771983,
        "Foreign exchange differences Adjustment":-1678269130,
        "Cash and Cash Equivalents at the end of period":1522610167671,
        "Depreciation and Amortisation":435817082372,
        "Operating profit before changes in working capital":3009588296958,
        "Purchase of fixed assets":-754460003456,
        "Gain on Dividend":192851388570,
        "Net Cash Flows from Investing Activities":-1821242533774,
        "Increase in charter captial":0,
        "Cash flows from financial activities":75558368003,
        "Collection of loans, proceeds from sales of debts instruments (Bn. VND)":1196918636,
        "Loans granted, purchases of debt instruments (Bn. VND)":-1302290439295
    },
    {
        "ticker":"VNM",
        "yearReport":2018,
        "lengthReport":3,
        "Cash and cash equivalents":1343435279374,
        "Unrealized foreign exchange gain\/loss":-1357776969,
        "Profit\/Loss from disposal of fixed assets":22784482067,
        "Profit\/Loss from investing activities":-5892802666,
        "Interest Expense":11981786169,
        "Interest income and dividends":-154195368449,
        "Increase\/Decrease in receivables":-242670243422,
        "Increase\/Decrease in inventories":502408308195,
        "Increase\/Decrease in payables":-696799651704,
        "Increase\/Decrease in prepaid expenses":20297499116,
        "Interest paid":-13598961804,
        "Business Income Tax paid":-352525024151,
        "Other receipts from operating activities":-149174000,
        "Other payments on operating activities":-211592389694,
        "Net cash inflows\/outflows from operating activities":2239965411571,
        "Proceeds from disposal of fixed assets":36327914820,
        "Investment in other entities":0,
        "Proceeds from divestment in other entities":297000000,
        "Payments for share repurchases":-370485840,
        "Proceeds from borrowings":38193734965,
        "Repayment of borrowings":-880855186260,
        "Dividends paid":-2902384504000,
        "Net increase\/decrease in cash and cash equivalents":-715991966821,
        "Foreign exchange differences Adjustment":3341352265,
        "Cash and Cash Equivalents at the end of period":630784664818,
        "Depreciation and Amortisation":410134236563,
        "Operating profit before changes in working capital":3234595049035,
        "Purchase of fixed assets":-735685538410,
        "Gain on Dividend":149506005109,
        "Net Cash Flows from Investing Activities":789459062743,
        "Increase in charter captial":0,
        "Cash flows from financial activities":-3745416441135,
        "Collection of loans, proceeds from sales of debts instruments (Bn. VND)":189361909797,
        "Loans granted, purchases of debt instruments (Bn. VND)":1149651771427
    },
    {
        "ticker":"VNM",
        "yearReport":2018,
        "lengthReport":2,
        "Cash and cash equivalents":563392699177,
        "Unrealized foreign exchange gain\/loss":1373082074,
        "Profit\/Loss from disposal of fixed assets":25991779370,
        "Profit\/Loss from investing activities":7564938916,
        "Interest Expense":17272008785,
        "Interest income and dividends":-183721795859,
        "Increase\/Decrease in receivables":50598543542,
        "Increase\/Decrease in inventories":-556307221605,
        "Increase\/Decrease in payables":264627245971,
        "Increase\/Decrease in prepaid expenses":-6315983562,
        "Interest paid":-15750004879,
        "Business Income Tax paid":-394072132165,
        "Other receipts from operating activities":0,
        "Other payments on operating activities":-149175286484,
        "Net cash inflows\/outflows from operating activities":2627531703991,
        "Proceeds from disposal of fixed assets":10912852049,
        "Investment in other entities":-12250000000,
        "Proceeds from divestment in other entities":0,
        "Payments for share repurchases":-1685141000,
        "Proceeds from borrowings":371675657187,
        "Repayment of borrowings":-166710243649,
        "Dividends paid":-2176870123500,
        "Net increase\/decrease in cash and cash equivalents":783230823186,
        "Foreign exchange differences Adjustment":-3188242989,
        "Cash and Cash Equivalents at the end of period":1343435279374,
        "Depreciation and Amortisation":395470414797,
        "Operating profit before changes in working capital":3433926543173,
        "Purchase of fixed assets":-1098217774830,
        "Gain on Dividend":175350527457,
        "Net Cash Flows from Investing Activities":129288970157,
        "Increase in charter captial":0,
        "Cash flows from financial activities":-1973589850962,
        "Collection of loans, proceeds from sales of debts instruments (Bn. VND)":1692702019,
        "Loans granted, purchases of debt instruments (Bn. VND)":1051800663462
    },
    {
        "ticker":"VNM",
        "yearReport":2018,
        "lengthReport":1,
        "Cash and cash equivalents":963335914164,
        "Unrealized foreign exchange gain\/loss":2139828092,
        "Profit\/Loss from disposal of fixed assets":-10016587338,
        "Profit\/Loss from investing activities":-14061854211,
        "Interest Expense":8555583980,
        "Interest income and dividends":-184754015176,
        "Increase\/Decrease in receivables":-548399424564,
        "Increase\/Decrease in inventories":-371241518450,
        "Increase\/Decrease in payables":-780464995133,
        "Increase\/Decrease in prepaid expenses":10620079733,
        "Interest paid":-7711647185,
        "Business Income Tax paid":-320083426899,
        "Other receipts from operating activities":149174000,
        "Other payments on operating activities":-731057695701,
        "Net cash inflows\/outflows from operating activities":633553979333,
        "Proceeds from disposal of fixed assets":22730847793,
        "Investment in other entities":0,
        "Proceeds from divestment in other entities":1215000000,
        "Payments for share repurchases":-636147800,
        "Proceeds from borrowings":1940705852193,
        "Repayment of borrowings":-654811071845,
        "Dividends paid":-2176917780000,
        "Net increase\/decrease in cash and cash equivalents":-400755303429,
        "Foreign exchange differences Adjustment":812088442,
        "Cash and Cash Equivalents at the end of period":563392699177,
        "Depreciation and Amortisation":385210648619,
        "Operating profit before changes in working capital":3381743433532,
        "Purchase of fixed assets":-597432120943,
        "Gain on Dividend":130071841502,
        "Net Cash Flows from Investing Activities":-142650135310,
        "Increase in charter captial":0,
        "Cash flows from financial activities":-891659147452,
        "Collection of loans, proceeds from sales of debts instruments (Bn. VND)":764296338,
        "Loans granted, purchases of debt instruments (Bn. VND)":300000000000
    },
    {
        "ticker":"VNM",
        "yearReport":2017,
        "lengthReport":4,
        "Cash and cash equivalents":668414723359,
        "Unrealized foreign exchange gain\/loss":-1005453891,
        "Profit\/Loss from disposal of fixed assets":-3252258594,
        "Profit\/Loss from investing activities":-23150316785,
        "Interest Expense":5015216618,
        "Interest income and dividends":-192250150991,
        "Increase\/Decrease in receivables":-119692805765,
        "Increase\/Decrease in inventories":-275746944565,
        "Increase\/Decrease in payables":104750988551,
        "Increase\/Decrease in prepaid expenses":-3128340447,
        "Interest paid":-19625043160,
        "Business Income Tax paid":-882543002721,
        "Other receipts from operating activities":0,
        "Other payments on operating activities":-9243768130,
        "Net cash inflows\/outflows from operating activities":1046278805204,
        "Proceeds from disposal of fixed assets":49973489631,
        "Investment in other entities":13170000000,
        "Proceeds from divestment in other entities":29535359489,
        "Payments for share repurchases":-1452559480,
        "Proceeds from borrowings":801702959833,
        "Repayment of borrowings":-1107022314733,
        "Dividends paid":-4808323,
        "Net increase\/decrease in cash and cash equivalents":293027494342,
        "Foreign exchange differences Adjustment":1893696463,
        "Cash and Cash Equivalents at the end of period":963335914164,
        "Depreciation and Amortisation":361296133295,
        "Operating profit before changes in working capital":2251507721441,
        "Purchase of fixed assets":-1014868596476,
        "Gain on Dividend":247146083058,
        "Net Cash Flows from Investing Activities":-446474588159,
        "Increase in charter captial":0,
        "Cash flows from financial activities":-306776722703,
        "Collection of loans, proceeds from sales of debts instruments (Bn. VND)":-1429238222,
        "Loans granted, purchases of debt instruments (Bn. VND)":229998314361
    },
    {
        "ticker":"VNM",
        "yearReport":2017,
        "lengthReport":3,
        "Cash and cash equivalents":590906789944,
        "Unrealized foreign exchange gain\/loss":-235275295,
        "Profit\/Loss from disposal of fixed assets":9521857674,
        "Profit\/Loss from investing activities":-8393748492,
        "Interest Expense":7006245652,
        "Interest income and dividends":-196524797524,
        "Increase\/Decrease in receivables":-381497100128,
        "Increase\/Decrease in inventories":309819135860,
        "Increase\/Decrease in payables":-84783736100,
        "Increase\/Decrease in prepaid expenses":11749845419,
        "Interest paid":-7006245652,
        "Business Income Tax paid":-428250958947,
        "Other receipts from operating activities":0,
        "Other payments on operating activities":-258595612325,
        "Net cash inflows\/outflows from operating activities":2516894947957,
        "Proceeds from disposal of fixed assets":12754474532,
        "Investment in other entities":-100000000000,
        "Proceeds from divestment in other entities":0,
        "Payments for share repurchases":-54360575098,
        "Proceeds from borrowings":570803480214,
        "Repayment of borrowings":-487796582887,
        "Dividends paid":-2903116484782,
        "Net increase\/decrease in cash and cash equivalents":76848131720,
        "Foreign exchange differences Adjustment":659801695,
        "Cash and Cash Equivalents at the end of period":668414723359,
        "Depreciation and Amortisation":313041751008,
        "Operating profit before changes in working capital":3355459619830,
        "Purchase of fixed assets":-530926922208,
        "Gain on Dividend":201425742917,
        "Net Cash Flows from Investing Activities":434423346316,
        "Increase in charter captial":0,
        "Cash flows from financial activities":-2874470162553,
        "Collection of loans, proceeds from sales of debts instruments (Bn. VND)":1158251597,
        "Loans granted, purchases of debt instruments (Bn. VND)":850011799478
    },
    {
        "ticker":"VNM",
        "yearReport":2017,
        "lengthReport":2,
        "Cash and cash equivalents":2216760721249,
        "Unrealized foreign exchange gain\/loss":2911766974,
        "Profit\/Loss from disposal of fixed assets":-1399766352,
        "Profit\/Loss from investing activities":-18980009176,
        "Interest Expense":4023632084,
        "Interest income and dividends":-195028555940,
        "Increase\/Decrease in receivables":-562133549735,
        "Increase\/Decrease in inventories":-291495672990,
        "Increase\/Decrease in payables":864673523943,
        "Increase\/Decrease in prepaid expenses":-20244107430,
        "Interest paid":-4023632084,
        "Business Income Tax paid":-433641587858,
        "Other receipts from operating activities":0,
        "Other payments on operating activities":-107265614975,
        "Net cash inflows\/outflows from operating activities":3003135610506,
        "Proceeds from disposal of fixed assets":44351183120,
        "Investment in other entities":0,
        "Proceeds from divestment in other entities":0,
        "Payments for share repurchases":-87145916880,
        "Proceeds from borrowings":726000210240,
        "Repayment of borrowings":-792260176986,
        "Dividends paid":-2902686424000,
        "Net increase\/decrease in cash and cash equivalents":-1631189115197,
        "Foreign exchange differences Adjustment":5335183892,
        "Cash and Cash Equivalents at the end of period":590906789944,
        "Depreciation and Amortisation":314288377307,
        "Operating profit before changes in working capital":3557266251635,
        "Purchase of fixed assets":-609408193544,
        "Gain on Dividend":117246260959,
        "Net Cash Flows from Investing Activities":-1578232418077,
        "Increase in charter captial":0,
        "Cash flows from financial activities":-3056092307626,
        "Collection of loans, proceeds from sales of debts instruments (Bn. VND)":167837165623,
        "Loans granted, purchases of debt instruments (Bn. VND)":-1298258834235
    },
    {
        "ticker":"VNM",
        "yearReport":2017,
        "lengthReport":1,
        "Cash and cash equivalents":655423095436,
        "Unrealized foreign exchange gain\/loss":2045337290,
        "Profit\/Loss from disposal of fixed assets":6756455655,
        "Profit\/Loss from investing activities":-16609907192,
        "Interest Expense":13393474209,
        "Interest income and dividends":-186324026005,
        "Increase\/Decrease in receivables":-535822761013,
        "Increase\/Decrease in inventories":575893123634,
        "Increase\/Decrease in payables":74089011677,
        "Increase\/Decrease in prepaid expenses":1622947718,
        "Interest paid":-34476094310,
        "Business Income Tax paid":-189074031088,
        "Other receipts from operating activities":0,
        "Other payments on operating activities":-462882084959,
        "Net cash inflows\/outflows from operating activities":3035285161422,
        "Proceeds from disposal of fixed assets":13632259257,
        "Investment in other entities":0,
        "Proceeds from divestment in other entities":0,
        "Payments for share repurchases":-139441921480,
        "Proceeds from borrowings":678543472183,
        "Repayment of borrowings":-1837107787294,
        "Dividends paid":0,
        "Net increase\/decrease in cash and cash equivalents":1556573563804,
        "Foreign exchange differences Adjustment":4764062009,
        "Cash and Cash Equivalents at the end of period":2216760721249,
        "Depreciation and Amortisation":311243892290,
        "Operating profit before changes in working capital":3605935049763,
        "Purchase of fixed assets":-517785777958,
        "Gain on Dividend":189141986132,
        "Net Cash Flows from Investing Activities":-180705361027,
        "Increase in charter captial":0,
        "Cash flows from financial activities":-1298006236591,
        "Collection of loans, proceeds from sales of debts instruments (Bn. VND)":134306171542,
        "Loans granted, purchases of debt instruments (Bn. VND)":0
    },
    {
        "ticker":"VNM",
        "yearReport":2016,
        "lengthReport":4,
        "Cash and cash equivalents":772572092518,
        "Unrealized foreign exchange gain\/loss":-2421530243,
        "Profit\/Loss from disposal of fixed assets":-11837673491,
        "Profit\/Loss from investing activities":-625995076746,
        "Interest Expense":19574144919,
        "Interest income and dividends":490446032083,
        "Increase\/Decrease in receivables":683975707234,
        "Increase\/Decrease in inventories":-729218911374,
        "Increase\/Decrease in payables":294247502773,
        "Increase\/Decrease in prepaid expenses":-15910075449,
        "Interest paid":-6359793658,
        "Business Income Tax paid":-696468005657,
        "Other receipts from operating activities":0,
        "Other payments on operating activities":-86405240153,
        "Net cash inflows\/outflows from operating activities":1833566716987,
        "Proceeds from disposal of fixed assets":14992224440,
        "Investment in other entities":0,
        "Proceeds from divestment in other entities":1800000000,
        "Payments for share repurchases":-1064835600,
        "Proceeds from borrowings":793714910086,
        "Repayment of borrowings":-823150958440,
        "Dividends paid":0,
        "Net increase\/decrease in cash and cash equivalents":-112195511910,
        "Foreign exchange differences Adjustment":-4953485172,
        "Cash and Cash Equivalents at the end of period":655423095436,
        "Depreciation and Amortisation":305898825987,
        "Operating profit before changes in working capital":2389705533271,
        "Purchase of fixed assets":-563825266202,
        "Gain on Dividend":148429296008,
        "Net Cash Flows from Investing Activities":-1915261344943,
        "Increase in charter captial":0,
        "Cash flows from financial activities":-30500883954,
        "Collection of loans, proceeds from sales of debts instruments (Bn. VND)":-68402720000,
        "Loans granted, purchases of debt instruments (Bn. VND)":-1448254879189
    },
    {
        "ticker":"VNM",
        "yearReport":2016,
        "lengthReport":3,
        "Cash and cash equivalents":3059808166107,
        "Unrealized foreign exchange gain\/loss":-1122641475,
        "Profit\/Loss from disposal of fixed assets":-2944306481,
        "Profit\/Loss from investing activities":11186138007,
        "Interest Expense":9907013298,
        "Interest income and dividends":-158222932118,
        "Increase\/Decrease in receivables":-214469721916,
        "Increase\/Decrease in inventories":415554950933,
        "Increase\/Decrease in payables":172466280018,
        "Increase\/Decrease in prepaid expenses":-32188309264,
        "Interest paid":-17902089394,
        "Business Income Tax paid":-526612749831,
        "Other receipts from operating activities":0,
        "Other payments on operating activities":-325166832602,
        "Net cash inflows\/outflows from operating activities":2687584251069,
        "Proceeds from disposal of fixed assets":19136893916,
        "Investment in other entities":0,
        "Proceeds from divestment in other entities":0,
        "Payments for share repurchases":-459688141,
        "Proceeds from borrowings":2403872588708,
        "Repayment of borrowings":-2434361645825,
        "Dividends paid":-4838199696000,
        "Net increase\/decrease in cash and cash equivalents":-2291073265072,
        "Foreign exchange differences Adjustment":3837191483,
        "Cash and Cash Equivalents at the end of period":772572092518,
        "Depreciation and Amortisation":299199643751,
        "Operating profit before changes in working capital":3204873389625,
        "Purchase of fixed assets":-274831031269,
        "Gain on Dividend":111424073132,
        "Net Cash Flows from Investing Activities":-464474115603,
        "Increase in charter captial":354965040720,
        "Cash flows from financial activities":-4514183400538,
        "Collection of loans, proceeds from sales of debts instruments (Bn. VND)":-318119017671,
        "Loans granted, purchases of debt instruments (Bn. VND)":-2085033711
    },
    {
        "ticker":"VNM",
        "yearReport":2016,
        "lengthReport":2,
        "Cash and cash equivalents":1228329938789,
        "Unrealized foreign exchange gain\/loss":-2654178472,
        "Profit\/Loss from disposal of fixed assets":14781979972,
        "Profit\/Loss from investing activities":138855035365,
        "Interest Expense":8704401479,
        "Interest income and dividends":-332223099965,
        "Increase\/Decrease in receivables":-8767370365,
        "Increase\/Decrease in inventories":-379289285036,
        "Increase\/Decrease in payables":271245446363,
        "Increase\/Decrease in prepaid expenses":19322587690,
        "Interest paid":-5530486223,
        "Business Income Tax paid":-419991024402,
        "Other receipts from operating activities":0,
        "Other payments on operating activities":-20535485116,
        "Net cash inflows\/outflows from operating activities":2953089687014,
        "Proceeds from disposal of fixed assets":8239997175,
        "Investment in other entities":0,
        "Proceeds from divestment in other entities":0,
        "Payments for share repurchases":-67797170608,
        "Proceeds from borrowings":194864990907,
        "Repayment of borrowings":-239776180663,
        "Dividends paid":-2400278796000,
        "Net increase\/decrease in cash and cash equivalents":1837720727033,
        "Foreign exchange differences Adjustment":-6242499715,
        "Cash and Cash Equivalents at the end of period":3059808166107,
        "Depreciation and Amortisation":296186157902,
        "Operating profit before changes in working capital":3496635280093,
        "Purchase of fixed assets":-124416915644,
        "Gain on Dividend":190774479178,
        "Net Cash Flows from Investing Activities":1397618196383,
        "Increase in charter captial":0,
        "Cash flows from financial activities":-2512987156364,
        "Collection of loans, proceeds from sales of debts instruments (Bn. VND)":385250985674,
        "Loans granted, purchases of debt instruments (Bn. VND)":937769650000
    },
    {
        "ticker":"VNM",
        "yearReport":2016,
        "lengthReport":1,
        "Cash and cash equivalents":1358682600684,
        "Unrealized foreign exchange gain\/loss":4879483004,
        "Profit\/Loss from disposal of fixed assets":0,
        "Profit\/Loss from investing activities":-159026751087,
        "Interest Expense":8313790353,
        "Interest income and dividends":0,
        "Increase\/Decrease in receivables":-643813097813,
        "Increase\/Decrease in inventories":-343931914727,
        "Increase\/Decrease in payables":-407564684707,
        "Increase\/Decrease in prepaid expenses":112828925191,
        "Interest paid":-4411251035,
        "Business Income Tax paid":-128170725101,
        "Other receipts from operating activities":0,
        "Other payments on operating activities":-442089418988,
        "Net cash inflows\/outflows from operating activities":915540651263,
        "Proceeds from disposal of fixed assets":7957839467,
        "Investment in other entities":-8100000000,
        "Proceeds from divestment in other entities":0,
        "Payments for share repurchases":0,
        "Proceeds from borrowings":679432646891,
        "Repayment of borrowings":-762757530671,
        "Dividends paid":0,
        "Net increase\/decrease in cash and cash equivalents":-131453615162,
        "Foreign exchange differences Adjustment":1100953267,
        "Cash and Cash Equivalents at the end of period":1228329938789,
        "Depreciation and Amortisation":289552380294,
        "Operating profit before changes in working capital":2772301168443,
        "Purchase of fixed assets":-178539539234,
        "Gain on Dividend":151511215125,
        "Net Cash Flows from Investing Activities":-963669382645,
        "Increase in charter captial":0,
        "Cash flows from financial activities":-83324883780,
        "Collection of loans, proceeds from sales of debts instruments (Bn. VND)":1270751997,
        "Loans granted, purchases of debt instruments (Bn. VND)":-937769650000
    },
    {
        "ticker":"VNM",
        "yearReport":2015,
        "lengthReport":4,
        "Cash and cash equivalents":1409857423245,
        "Unrealized foreign exchange gain\/loss":-1832703171,
        "Profit\/Loss from disposal of fixed assets":0,
        "Profit\/Loss from investing activities":-118645695328,
        "Interest Expense":8538729589,
        "Interest income and dividends":0,
        "Increase\/Decrease in receivables":220420988772,
        "Increase\/Decrease in inventories":-187776432431,
        "Increase\/Decrease in payables":-131452125151,
        "Increase\/Decrease in prepaid expenses":-84322648065,
        "Interest paid":-4302072489,
        "Business Income Tax paid":-532921429124,
        "Other receipts from operating activities":0,
        "Other payments on operating activities":-154964043556,
        "Net cash inflows\/outflows from operating activities":1590690156909,
        "Proceeds from disposal of fixed assets":-7757208485,
        "Investment in other entities":0,
        "Proceeds from divestment in other entities":8843058117,
        "Payments for share repurchases":0,
        "Proceeds from borrowings":922113056493,
        "Repayment of borrowings":-816410975120,
        "Dividends paid":-1549950354,
        "Net increase\/decrease in cash and cash equivalents":-79769312894,
        "Foreign exchange differences Adjustment":28594490333,
        "Cash and Cash Equivalents at the end of period":1358682600684,
        "Depreciation and Amortisation":282693269930,
        "Operating profit before changes in working capital":2466019070314,
        "Purchase of fixed assets":-199490388329,
        "Gain on Dividend":171300066306,
        "Net Cash Flows from Investing Activities":-1775395992731,
        "Increase in charter captial":784391909,
        "Cash flows from financial activities":104936522928,
        "Collection of loans, proceeds from sales of debts instruments (Bn. VND)":-438849070340,
        "Loans granted, purchases of debt instruments (Bn. VND)":-1309442450000
    },
    {
        "ticker":"VNM",
        "yearReport":2015,
        "lengthReport":3,
        "Cash and cash equivalents":1854221704170,
        "Unrealized foreign exchange gain\/loss":4070666998,
        "Profit\/Loss from disposal of fixed assets":0,
        "Profit\/Loss from investing activities":-133072431101,
        "Interest Expense":7823572163,
        "Interest income and dividends":0,
        "Increase\/Decrease in receivables":46092094373,
        "Increase\/Decrease in inventories":104484498560,
        "Increase\/Decrease in payables":283014730199,
        "Increase\/Decrease in prepaid expenses":3517086155,
        "Interest paid":-6933611285,
        "Business Income Tax paid":-505175219378,
        "Other receipts from operating activities":-22765700000,
        "Other payments on operating activities":-153058969212,
        "Net cash inflows\/outflows from operating activities":2578554111239,
        "Proceeds from disposal of fixed assets":12665980902,
        "Investment in other entities":-80161500899,
        "Proceeds from divestment in other entities":3532122500,
        "Payments for share repurchases":0,
        "Proceeds from borrowings":1745095032790,
        "Repayment of borrowings":-1237171192396,
        "Dividends paid":-4000474416000,
        "Net increase\/decrease in cash and cash equivalents":-427145837494,
        "Foreign exchange differences Adjustment":-17218443431,
        "Cash and Cash Equivalents at the end of period":1409857423245,
        "Depreciation and Amortisation":276279699878,
        "Operating profit before changes in working capital":2706552927972,
        "Purchase of fixed assets":-286419670818,
        "Gain on Dividend":161224879154,
        "Net Cash Flows from Investing Activities":464530612836,
        "Increase in charter captial":22320014037,
        "Cash flows from financial activities":-3470230561569,
        "Collection of loans, proceeds from sales of debts instruments (Bn. VND)":440826441325,
        "Loans granted, purchases of debt instruments (Bn. VND)":212862360672
    },
    {
        "ticker":"VNM",
        "yearReport":2015,
        "lengthReport":2,
        "Cash and cash equivalents":1227505962892,
        "Unrealized foreign exchange gain\/loss":1712378954,
        "Profit\/Loss from disposal of fixed assets":0,
        "Profit\/Loss from investing activities":-168426171453,
        "Interest Expense":6783629838,
        "Interest income and dividends":0,
        "Increase\/Decrease in receivables":-18923403981,
        "Increase\/Decrease in inventories":63761443246,
        "Increase\/Decrease in payables":-7743119813,
        "Increase\/Decrease in prepaid expenses":-19321562854,
        "Interest paid":-6253423958,
        "Business Income Tax paid":-345113069246,
        "Other receipts from operating activities":0,
        "Other payments on operating activities":-93588930597,
        "Net cash inflows\/outflows from operating activities":2300992832381,
        "Proceeds from disposal of fixed assets":10561319038,
        "Investment in other entities":20982476,
        "Proceeds from divestment in other entities":1527061268,
        "Payments for share repurchases":0,
        "Proceeds from borrowings":1306014281986,
        "Repayment of borrowings":-1365990956702,
        "Dividends paid":-2000237208000,
        "Net increase\/decrease in cash and cash equivalents":632712319710,
        "Foreign exchange differences Adjustment":-5996578432,
        "Cash and Cash Equivalents at the end of period":1854221704170,
        "Depreciation and Amortisation":271404668281,
        "Operating profit before changes in working capital":2726848514678,
        "Purchase of fixed assets":-369439681479,
        "Gain on Dividend":33639943837,
        "Net Cash Flows from Investing Activities":307561377137,
        "Increase in charter captial":84371992908,
        "Cash flows from financial activities":-1975841889808,
        "Collection of loans, proceeds from sales of debts instruments (Bn. VND)":0,
        "Loans granted, purchases of debt instruments (Bn. VND)":631251751997
    },
    {
        "ticker":"VNM",
        "yearReport":2015,
        "lengthReport":1,
        "Cash and cash equivalents":1527875428216,
        "Unrealized foreign exchange gain\/loss":21503375,
        "Profit\/Loss from disposal of fixed assets":0,
        "Profit\/Loss from investing activities":-120953311467,
        "Interest Expense":8131520374,
        "Interest income and dividends":0,
        "Increase\/Decrease in receivables":-82027954407,
        "Increase\/Decrease in inventories":-479008754986,
        "Increase\/Decrease in payables":340520121347,
        "Increase\/Decrease in prepaid expenses":64253223010,
        "Interest paid":-9841219741,
        "Business Income Tax paid":-422400933527,
        "Other receipts from operating activities":22765700000,
        "Other payments on operating activities":-314040254076,
        "Net cash inflows\/outflows from operating activities":1188914007159,
        "Proceeds from disposal of fixed assets":28530489589,
        "Investment in other entities":-20982476,
        "Proceeds from divestment in other entities":0,
        "Payments for share repurchases":0,
        "Proceeds from borrowings":0,
        "Repayment of borrowings":-363166758519,
        "Dividends paid":0,
        "Net increase\/decrease in cash and cash equivalents":-297630183585,
        "Foreign exchange differences Adjustment":-2739281739,
        "Cash and Cash Equivalents at the end of period":1227505962892,
        "Depreciation and Amortisation":266697914650,
        "Operating profit before changes in working capital":2068694079539,
        "Purchase of fixed assets":-212491480427,
        "Gain on Dividend":94718653758,
        "Net Cash Flows from Investing Activities":-1123377432225,
        "Increase in charter captial":0,
        "Cash flows from financial activities":-363166758519,
        "Collection of loans, proceeds from sales of debts instruments (Bn. VND)":0,
        "Loans granted, purchases of debt instruments (Bn. VND)":-1034114112669
    },
    {
        "ticker":"VNM",
        "yearReport":2014,
        "lengthReport":4,
        "Cash and cash equivalents":670329547281,
        "Unrealized foreign exchange gain\/loss":9183282297,
        "Profit\/Loss from disposal of fixed assets":0,
        "Profit\/Loss from investing activities":-137459574325,
        "Interest Expense":9075994158,
        "Interest income and dividends":0,
        "Increase\/Decrease in receivables":-284555594237,
        "Increase\/Decrease in inventories":-140172757190,
        "Increase\/Decrease in payables":126060617090,
        "Increase\/Decrease in prepaid expenses":-55343121010,
        "Interest paid":-7675427249,
        "Business Income Tax paid":-383310768661,
        "Other receipts from operating activities":45152745658,
        "Other payments on operating activities":-73105950595,
        "Net cash inflows\/outflows from operating activities":1544195545977,
        "Proceeds from disposal of fixed assets":13733258951,
        "Investment in other entities":-2011694925,
        "Proceeds from divestment in other entities":17213461471,
        "Payments for share repurchases":0,
        "Proceeds from borrowings":-3666195544,
        "Repayment of borrowings":-6438074389,
        "Dividends paid":-488201,
        "Net increase\/decrease in cash and cash equivalents":857423704134,
        "Foreign exchange differences Adjustment":122176801,
        "Cash and Cash Equivalents at the end of period":1527875428216,
        "Depreciation and Amortisation":263064953718,
        "Operating profit before changes in working capital":2317145802171,
        "Purchase of fixed assets":-288398582496,
        "Gain on Dividend":133048456472,
        "Net Cash Flows from Investing Activities":-676835768050,
        "Increase in charter captial":168684341,
        "Cash flows from financial activities":-9936073793,
        "Collection of loans, proceeds from sales of debts instruments (Bn. VND)":0,
        "Loans granted, purchases of debt instruments (Bn. VND)":-550420667523
    },
    {
        "ticker":"VNM",
        "yearReport":2014,
        "lengthReport":3,
        "Cash and cash equivalents":1219936043702,
        "Unrealized foreign exchange gain\/loss":-13342408990,
        "Profit\/Loss from disposal of fixed assets":-6234942158,
        "Profit\/Loss from investing activities":-368448360666,
        "Interest Expense":7423763901,
        "Interest income and dividends":248292374936,
        "Increase\/Decrease in receivables":-283428430610,
        "Increase\/Decrease in inventories":700224588589,
        "Increase\/Decrease in payables":-547820013811,
        "Increase\/Decrease in prepaid expenses":19356738147,
        "Interest paid":-3941104832,
        "Business Income Tax paid":-448978208152,
        "Other receipts from operating activities":0,
        "Other payments on operating activities":-144373533102,
        "Net cash inflows\/outflows from operating activities":1145872473683,
        "Proceeds from disposal of fixed assets":13504052453,
        "Investment in other entities":86728260,
        "Proceeds from divestment in other entities":-86515208,
        "Payments for share repurchases":0,
        "Proceeds from borrowings":1241880467897,
        "Repayment of borrowings":-1419835457,
        "Dividends paid":-1666867855129,
        "Net increase\/decrease in cash and cash equivalents":-547977569163,
        "Foreign exchange differences Adjustment":-1628927258,
        "Cash and Cash Equivalents at the end of period":670329547281,
        "Depreciation and Amortisation":261083845708,
        "Operating profit before changes in working capital":1854832437454,
        "Purchase of fixed assets":-281081876600,
        "Gain on Dividend":129387586257,
        "Net Cash Flows from Investing Activities":-1336393923444,
        "Increase in charter captial":68951103287,
        "Cash flows from financial activities":-357456119402,
        "Collection of loans, proceeds from sales of debts instruments (Bn. VND)":1801892101394,
        "Loans granted, purchases of debt instruments (Bn. VND)":-3000096000000
    },
    {
        "ticker":"VNM",
        "yearReport":2014,
        "lengthReport":2,
        "Cash and cash equivalents":1193310867797,
        "Unrealized foreign exchange gain\/loss":-2385211951,
        "Profit\/Loss from disposal of fixed assets":6234942158,
        "Profit\/Loss from investing activities":104577152258,
        "Interest Expense":12410656942,
        "Interest income and dividends":-248292374936,
        "Increase\/Decrease in receivables":209752272202,
        "Increase\/Decrease in inventories":-491003751413,
        "Increase\/Decrease in payables":296947233045,
        "Increase\/Decrease in prepaid expenses":-4082278741,
        "Interest paid":-12454117049,
        "Business Income Tax paid":-319907772294,
        "Other receipts from operating activities":966420000,
        "Other payments on operating activities":-6432953215,
        "Net cash inflows\/outflows from operating activities":1784183050439,
        "Proceeds from disposal of fixed assets":23949522845,
        "Investment in other entities":-572351069,
        "Proceeds from divestment in other entities":498622064,
        "Payments for share repurchases":-75788000,
        "Proceeds from borrowings":240956160318,
        "Repayment of borrowings":-220059210062,
        "Dividends paid":-1666874642000,
        "Net increase\/decrease in cash and cash equivalents":25051241621,
        "Foreign exchange differences Adjustment":1573934284,
        "Cash and Cash Equivalents at the end of period":1219936043702,
        "Depreciation and Amortisation":256700612080,
        "Operating profit before changes in working capital":2110397997904,
        "Purchase of fixed assets":-121134383337,
        "Gain on Dividend":279474544120,
        "Net Cash Flows from Investing Activities":-114380045377,
        "Increase in charter captial":1301716303,
        "Cash flows from financial activities":-1644751763441,
        "Collection of loans, proceeds from sales of debts instruments (Bn. VND)":-1796596000000,
        "Loans granted, purchases of debt instruments (Bn. VND)":1500000000000
    },
    {
        "ticker":"VNM",
        "yearReport":2014,
        "lengthReport":1,
        "Cash and cash equivalents":2745645325950,
        "Unrealized foreign exchange gain\/loss":-1860468523,
        "Profit\/Loss from disposal of fixed assets":0,
        "Profit\/Loss from investing activities":-126621935996,
        "Interest Expense":10671322757,
        "Interest income and dividends":0,
        "Increase\/Decrease in receivables":227802236917,
        "Increase\/Decrease in inventories":-614365683108,
        "Increase\/Decrease in payables":84031617046,
        "Increase\/Decrease in prepaid expenses":45574782583,
        "Interest paid":-10671322757,
        "Business Income Tax paid":-369710651438,
        "Other receipts from operating activities":0,
        "Other payments on operating activities":-379321936739,
        "Net cash inflows\/outflows from operating activities":854072470471,
        "Proceeds from disposal of fixed assets":2707450005,
        "Investment in other entities":-175474400,
        "Proceeds from divestment in other entities":2122893144,
        "Payments for share repurchases":-243814000,
        "Proceeds from borrowings":11804394842,
        "Repayment of borrowings":-5966180000,
        "Dividends paid":-666771088800,
        "Net increase\/decrease in cash and cash equivalents":-1552211967043,
        "Foreign exchange differences Adjustment":-122491110,
        "Cash and Cash Equivalents at the end of period":1193310867797,
        "Depreciation and Amortisation":251880590533,
        "Operating profit before changes in working capital":1870733427967,
        "Purchase of fixed assets":-168331439284,
        "Gain on Dividend":18568820979,
        "Net Cash Flows from Investing Activities":-1745107749556,
        "Increase in charter captial":0,
        "Cash flows from financial activities":-661176687958,
        "Collection of loans, proceeds from sales of debts instruments (Bn. VND)":0,
        "Loans granted, purchases of debt instruments (Bn. VND)":-1600000000000
    },
    {
        "ticker":"VNM",
        "yearReport":2013,
        "lengthReport":4,
        "Cash and cash equivalents":1684436360678,
        "Unrealized foreign exchange gain\/loss":1846201913,
        "Profit\/Loss from disposal of fixed assets":0,
        "Profit\/Loss from investing activities":-126202558548,
        "Interest Expense":104027048,
        "Interest income and dividends":0,
        "Increase\/Decrease in receivables":16245370232,
        "Increase\/Decrease in inventories":13030704982,
        "Increase\/Decrease in payables":288107196577,
        "Increase\/Decrease in prepaid expenses":-19647393735,
        "Interest paid":-104027048,
        "Business Income Tax paid":-381435472567,
        "Other receipts from operating activities":15000000,
        "Other payments on operating activities":-30564397414,
        "Net cash inflows\/outflows from operating activities":1845521833334,
        "Proceeds from disposal of fixed assets":5168055655,
        "Investment in other entities":-124805693826,
        "Proceeds from divestment in other entities":0,
        "Payments for share repurchases":-114858000,
        "Proceeds from borrowings":0,
        "Repayment of borrowings":0,
        "Dividends paid":0,
        "Net increase\/decrease in cash and cash equivalents":1061158759715,
        "Foreign exchange differences Adjustment":50205557,
        "Cash and Cash Equivalents at the end of period":2745645325950,
        "Depreciation and Amortisation":234338576859,
        "Operating profit before changes in working capital":1959874852307,
        "Purchase of fixed assets":-413858030707,
        "Gain on Dividend":49247453259,
        "Net Cash Flows from Investing Activities":-784248215619,
        "Increase in charter captial":0,
        "Cash flows from financial activities":-114858000,
        "Collection of loans, proceeds from sales of debts instruments (Bn. VND)":50000000000,
        "Loans granted, purchases of debt instruments (Bn. VND)":-350000000000
    },
    {
        "ticker":"VNM",
        "yearReport":2013,
        "lengthReport":3,
        "Cash and cash equivalents":812485229333,
        "Unrealized foreign exchange gain\/loss":14811246488,
        "Profit\/Loss from disposal of fixed assets":1490563589,
        "Profit\/Loss from investing activities":-17686524438,
        "Interest Expense":0,
        "Interest income and dividends":-104497829984,
        "Increase\/Decrease in receivables":-100854666397,
        "Increase\/Decrease in inventories":620615866424,
        "Increase\/Decrease in payables":-35627466875,
        "Increase\/Decrease in prepaid expenses":11983677151,
        "Interest paid":0,
        "Business Income Tax paid":-440417416152,
        "Other receipts from operating activities":19271912000,
        "Other payments on operating activities":-158618310985,
        "Net cash inflows\/outflows from operating activities":2085802558418,
        "Proceeds from disposal of fixed assets":3483548063,
        "Investment in other entities":0,
        "Proceeds from divestment in other entities":3127205437,
        "Payments for share repurchases":-129847000,
        "Proceeds from borrowings":0,
        "Repayment of borrowings":0,
        "Dividends paid":-1666951482000,
        "Net increase\/decrease in cash and cash equivalents":873714166761,
        "Foreign exchange differences Adjustment":-1763035416,
        "Cash and Cash Equivalents at the end of period":1684436360678,
        "Depreciation and Amortisation":217046141830,
        "Operating profit before changes in working capital":2169448963252,
        "Purchase of fixed assets":-471825503988,
        "Gain on Dividend":68012306772,
        "Net Cash Flows from Investing Activities":454992937343,
        "Increase in charter captial":0,
        "Cash flows from financial activities":-1667081329000,
        "Collection of loans, proceeds from sales of debts instruments (Bn. VND)":2195381059,
        "Loans granted, purchases of debt instruments (Bn. VND)":850000000000
    },
    {
        "ticker":"VNM",
        "yearReport":2013,
        "lengthReport":2,
        "Cash and cash equivalents":1633381902213,
        "Unrealized foreign exchange gain\/loss":7175018431,
        "Profit\/Loss from disposal of fixed assets":338734177,
        "Profit\/Loss from investing activities":71212152937,
        "Interest Expense":0,
        "Interest income and dividends":-191907183590,
        "Increase\/Decrease in receivables":-120146434803,
        "Increase\/Decrease in inventories":-129679584301,
        "Increase\/Decrease in payables":-40213526678,
        "Increase\/Decrease in prepaid expenses":-17971820185,
        "Interest paid":0,
        "Business Income Tax paid":-314240265642,
        "Other receipts from operating activities":1695349520,
        "Other payments on operating activities":-135320934589,
        "Net cash inflows\/outflows from operating activities":1567492953360,
        "Proceeds from disposal of fixed assets":9047347728,
        "Investment in other entities":0,
        "Proceeds from divestment in other entities":31800000000,
        "Payments for share repurchases":-175398959,
        "Proceeds from borrowings":0,
        "Repayment of borrowings":0,
        "Dividends paid":-1500283567800,
        "Net increase\/decrease in cash and cash equivalents":-824102893828,
        "Foreign exchange differences Adjustment":3206220948,
        "Cash and Cash Equivalents at the end of period":812485229333,
        "Depreciation and Amortisation":181791307800,
        "Operating profit before changes in working capital":2323370170038,
        "Purchase of fixed assets":-251080359470,
        "Gain on Dividend":122196131313,
        "Net Cash Flows from Investing Activities":-891136880429,
        "Increase in charter captial":0,
        "Cash flows from financial activities":-1500458966759,
        "Collection of loans, proceeds from sales of debts instruments (Bn. VND)":270000000000,
        "Loans granted, purchases of debt instruments (Bn. VND)":-1073100000000
    },
    {
        "ticker":"VNM",
        "yearReport":2013,
        "lengthReport":1,
        "Cash and cash equivalents":1252120160804,
        "Unrealized foreign exchange gain\/loss":-10767841818,
        "Profit\/Loss from disposal of fixed assets":0,
        "Profit\/Loss from investing activities":-74019283699,
        "Interest Expense":0,
        "Interest income and dividends":0,
        "Increase\/Decrease in receivables":-60152113353,
        "Increase\/Decrease in inventories":-314325531999,
        "Increase\/Decrease in payables":-240792526573,
        "Increase\/Decrease in prepaid expenses":-15625082924,
        "Interest paid":0,
        "Business Income Tax paid":-263889132445,
        "Other receipts from operating activities":2652000,
        "Other payments on operating activities":-367188520297,
        "Net cash inflows\/outflows from operating activities":681741219385,
        "Proceeds from disposal of fixed assets":3292438182,
        "Investment in other entities":0,
        "Proceeds from divestment in other entities":0,
        "Payments for share repurchases":-105339000,
        "Proceeds from borrowings":0,
        "Repayment of borrowings":0,
        "Dividends paid":0,
        "Net increase\/decrease in cash and cash equivalents":383423604539,
        "Foreign exchange differences Adjustment":-2161863130,
        "Cash and Cash Equivalents at the end of period":1633381902213,
        "Depreciation and Amortisation":153256896661,
        "Operating profit before changes in working capital":1943711474976,
        "Purchase of fixed assets":-353936443223,
        "Gain on Dividend":70095213874,
        "Net Cash Flows from Investing Activities":-298212275846,
        "Increase in charter captial":0,
        "Cash flows from financial activities":-105339000,
        "Collection of loans, proceeds from sales of debts instruments (Bn. VND)":32336515321,
        "Loans granted, purchases of debt instruments (Bn. VND)":-50000000000
    }
]